[
    {
        "Location": "Alabama",
        "24 or Younger,Dollars Outstanding(in billions)": "$1.67 ",
        "24 or Younger,Borrowers(in thousands)": "114.5",
        "25 to 34,Dollars Outstanding (in billions)": "$7.10 ",
        "25 to 34,Borrowers (in thousands)": "207.1",
        "35 to 49,Dollars Outstanding(in billions)": "$9.70 ",
        "35 to 49,Borrowers (in thousands)": "196.7",
        "50 to 61,Dollars Outstanding (in billions)": "$3.94 ",
        "50 to 61,Borrowers (in thousands)": "86.3",
        "62 and Older,Dollars Outstanding (in billions)": "$1.12 ",
        "62 and Older,Borrowers (in thousands)": "27.8"
    },
    {
        "Location": "Alaska",
        "24 or Younger,Dollars Outstanding(in billions)": "$0.10 ",
        "24 or Younger,Borrowers(in thousands)": "9.1",
        "25 to 34,Dollars Outstanding (in billions)": "$0.73 ",
        "25 to 34,Borrowers (in thousands)": "24.6",
        "35 to 49,Dollars Outstanding(in billions)": "$0.99 ",
        "35 to 49,Borrowers (in thousands)": "22.4",
        "50 to 61,Dollars Outstanding (in billions)": "$0.39 ",
        "50 to 61,Borrowers (in thousands)": "8.6",
        "62 and Older,Dollars Outstanding (in billions)": "$0.12 ",
        "62 and Older,Borrowers (in thousands)": "2.9"
    },
    {
        "Location": "Arizona",
        "24 or Younger,Dollars Outstanding(in billions)": "$1.59 ",
        "24 or Younger,Borrowers(in thousands)": "123.5",
        "25 to 34,Dollars Outstanding (in billions)": "$9.43 ",
        "25 to 34,Borrowers (in thousands)": "300.9",
        "35 to 49,Dollars Outstanding(in billions)": "$12.87 ",
        "35 to 49,Borrowers (in thousands)": "286.1",
        "50 to 61,Dollars Outstanding (in billions)": "$5.53 ",
        "50 to 61,Borrowers (in thousands)": "127.8",
        "62 and Older,Dollars Outstanding (in billions)": "$1.86 ",
        "62 and Older,Borrowers (in thousands)": "44.7"
    },
    {
        "Location": "Arkansas",
        "24 or Younger,Dollars Outstanding(in billions)": "$0.91 ",
        "24 or Younger,Borrowers(in thousands)": "69.2",
        "25 to 34,Dollars Outstanding (in billions)": "$4.04 ",
        "25 to 34,Borrowers (in thousands)": "131.6",
        "35 to 49,Dollars Outstanding(in billions)": "$5.50 ",
        "35 to 49,Borrowers (in thousands)": "124.3",
        "50 to 61,Dollars Outstanding (in billions)": "$2.02 ",
        "50 to 61,Borrowers (in thousands)": "48.8",
        "62 and Older,Dollars Outstanding (in billions)": "$0.56 ",
        "62 and Older,Borrowers (in thousands)": "14.7"
    },
    {
        "Location": "California",
        "24 or Younger,Dollars Outstanding(in billions)": "$8.31 ",
        "24 or Younger,Borrowers(in thousands)": "615.6",
        "25 to 34,Dollars Outstanding (in billions)": "$49.89 ",
        "25 to 34,Borrowers (in thousands)": "1,463.40",
        "35 to 49,Dollars Outstanding(in billions)": "$53.90 ",
        "35 to 49,Borrowers (in thousands)": "1,118.00",
        "50 to 61,Dollars Outstanding (in billions)": "$23.66 ",
        "50 to 61,Borrowers (in thousands)": "522.6",
        "62 and Older,Dollars Outstanding (in billions)": "$8.93 ",
        "62 and Older,Borrowers (in thousands)": "207.4"
    },
    {
        "Location": "Colorado",
        "24 or Younger,Dollars Outstanding(in billions)": "$1.59 ",
        "24 or Younger,Borrowers(in thousands)": "118.5",
        "25 to 34,Dollars Outstanding (in billions)": "$9.44 ",
        "25 to 34,Borrowers (in thousands)": "287.4",
        "35 to 49,Dollars Outstanding(in billions)": "$11.37 ",
        "35 to 49,Borrowers (in thousands)": "239.4",
        "50 to 61,Dollars Outstanding (in billions)": "$4.61 ",
        "50 to 61,Borrowers (in thousands)": "95.8",
        "62 and Older,Dollars Outstanding (in billions)": "$1.53 ",
        "62 and Older,Borrowers (in thousands)": "31.7"
    },
    {
        "Location": "Connecticut",
        "24 or Younger,Dollars Outstanding(in billions)": "$1.87 ",
        "24 or Younger,Borrowers(in thousands)": "116.2",
        "25 to 34,Dollars Outstanding (in billions)": "$5.87 ",
        "25 to 34,Borrowers (in thousands)": "170.4",
        "35 to 49,Dollars Outstanding(in billions)": "$5.16 ",
        "35 to 49,Borrowers (in thousands)": "118.3",
        "50 to 61,Dollars Outstanding (in billions)": "$3.36 ",
        "50 to 61,Borrowers (in thousands)": "68.1",
        "62 and Older,Dollars Outstanding (in billions)": "$1.21 ",
        "62 and Older,Borrowers (in thousands)": "23"
    },
    {
        "Location": "Delaware",
        "24 or Younger,Dollars Outstanding(in billions)": "$0.38 ",
        "24 or Younger,Borrowers(in thousands)": "24.8",
        "25 to 34,Dollars Outstanding (in billions)": "$1.44 ",
        "25 to 34,Borrowers (in thousands)": "42.2",
        "35 to 49,Dollars Outstanding(in billions)": "$1.68 ",
        "35 to 49,Borrowers (in thousands)": "35.1",
        "50 to 61,Dollars Outstanding (in billions)": "$0.94 ",
        "50 to 61,Borrowers (in thousands)": "18.1",
        "62 and Older,Dollars Outstanding (in billions)": "$0.29 ",
        "62 and Older,Borrowers (in thousands)": "5.8"
    },
    {
        "Location": "District of Columbia",
        "24 or Younger,Dollars Outstanding(in billions)": "$0.25 ",
        "24 or Younger,Borrowers(in thousands)": "13.6",
        "25 to 34,Dollars Outstanding (in billions)": "$2.79 ",
        "25 to 34,Borrowers (in thousands)": "49.2",
        "35 to 49,Dollars Outstanding(in billions)": "$2.45 ",
        "35 to 49,Borrowers (in thousands)": "34.7",
        "50 to 61,Dollars Outstanding (in billions)": "$0.68 ",
        "50 to 61,Borrowers (in thousands)": "13.2",
        "62 and Older,Dollars Outstanding (in billions)": "$0.29 ",
        "62 and Older,Borrowers (in thousands)": "6.7"
    },
    {
        "Location": "Florida",
        "24 or Younger,Dollars Outstanding(in billions)": "$5.02 ",
        "24 or Younger,Borrowers(in thousands)": "354.1",
        "25 to 34,Dollars Outstanding (in billions)": "$32.04 ",
        "25 to 34,Borrowers (in thousands)": "904.1",
        "35 to 49,Dollars Outstanding(in billions)": "$40.53 ",
        "35 to 49,Borrowers (in thousands)": "845.5",
        "50 to 61,Dollars Outstanding (in billions)": "$17.31 ",
        "50 to 61,Borrowers (in thousands)": "373.5",
        "62 and Older,Dollars Outstanding (in billions)": "$5.66 ",
        "62 and Older,Borrowers (in thousands)": "128.1"
    },
    {
        "Location": "Georgia",
        "24 or Younger,Dollars Outstanding(in billions)": "$4.08 ",
        "24 or Younger,Borrowers(in thousands)": "281.7",
        "25 to 34,Dollars Outstanding (in billions)": "$19.90 ",
        "25 to 34,Borrowers (in thousands)": "543.4",
        "35 to 49,Dollars Outstanding(in billions)": "$28.21 ",
        "35 to 49,Borrowers (in thousands)": "514.8",
        "50 to 61,Dollars Outstanding (in billions)": "$12.76 ",
        "50 to 61,Borrowers (in thousands)": "234",
        "62 and Older,Dollars Outstanding (in billions)": "$3.55 ",
        "62 and Older,Borrowers (in thousands)": "70.7"
    },
    {
        "Location": "Hawaii",
        "24 or Younger,Dollars Outstanding(in billions)": "$0.30 ",
        "24 or Younger,Borrowers(in thousands)": "22",
        "25 to 34,Dollars Outstanding (in billions)": "$1.29 ",
        "25 to 34,Borrowers (in thousands)": "41",
        "35 to 49,Dollars Outstanding(in billions)": "$1.71 ",
        "35 to 49,Borrowers (in thousands)": "35.2",
        "50 to 61,Dollars Outstanding (in billions)": "$0.87 ",
        "50 to 61,Borrowers (in thousands)": "17.3",
        "62 and Older,Dollars Outstanding (in billions)": "$0.33 ",
        "62 and Older,Borrowers (in thousands)": "6.8"
    },
    {
        "Location": "Idaho",
        "24 or Younger,Dollars Outstanding(in billions)": "$0.41 ",
        "24 or Younger,Borrowers(in thousands)": "35.6",
        "25 to 34,Dollars Outstanding (in billions)": "$2.09 ",
        "25 to 34,Borrowers (in thousands)": "74.7",
        "35 to 49,Dollars Outstanding(in billions)": "$3.21 ",
        "35 to 49,Borrowers (in thousands)": "73.7",
        "50 to 61,Dollars Outstanding (in billions)": "$1.12 ",
        "50 to 61,Borrowers (in thousands)": "26.4",
        "62 and Older,Dollars Outstanding (in billions)": "$0.35 ",
        "62 and Older,Borrowers (in thousands)": "8"
    },
    {
        "Location": "Illinois",
        "24 or Younger,Dollars Outstanding(in billions)": "$5.05 ",
        "24 or Younger,Borrowers(in thousands)": "326.4",
        "25 to 34,Dollars Outstanding (in billions)": "$21.07 ",
        "25 to 34,Borrowers (in thousands)": "570.6",
        "35 to 49,Dollars Outstanding(in billions)": "$21.10 ",
        "35 to 49,Borrowers (in thousands)": "433.4",
        "50 to 61,Dollars Outstanding (in billions)": "$10.93 ",
        "50 to 61,Borrowers (in thousands)": "221.2",
        "62 and Older,Dollars Outstanding (in billions)": "$3.67 ",
        "62 and Older,Borrowers (in thousands)": "81"
    },
    {
        "Location": "Indiana",
        "24 or Younger,Dollars Outstanding(in billions)": "$2.28 ",
        "24 or Younger,Borrowers(in thousands)": "164.5",
        "25 to 34,Dollars Outstanding (in billions)": "$9.24 ",
        "25 to 34,Borrowers (in thousands)": "309.4",
        "35 to 49,Dollars Outstanding(in billions)": "$11.69 ",
        "35 to 49,Borrowers (in thousands)": "276.9",
        "50 to 61,Dollars Outstanding (in billions)": "$5.21 ",
        "50 to 61,Borrowers (in thousands)": "121.6",
        "62 and Older,Dollars Outstanding (in billions)": "$1.50 ",
        "62 and Older,Borrowers (in thousands)": "35.4"
    },
    {
        "Location": "Iowa",
        "24 or Younger,Dollars Outstanding(in billions)": "$1.30 ",
        "24 or Younger,Borrowers(in thousands)": "92.4",
        "25 to 34,Dollars Outstanding (in billions)": "$4.38 ",
        "25 to 34,Borrowers (in thousands)": "150.1",
        "35 to 49,Dollars Outstanding(in billions)": "$4.95 ",
        "35 to 49,Borrowers (in thousands)": "124.2",
        "50 to 61,Dollars Outstanding (in billions)": "$2.05 ",
        "50 to 61,Borrowers (in thousands)": "52.7",
        "62 and Older,Dollars Outstanding (in billions)": "$0.59 ",
        "62 and Older,Borrowers (in thousands)": "15.2"
    },
    {
        "Location": "Kansas",
        "24 or Younger,Dollars Outstanding(in billions)": "$1.01 ",
        "24 or Younger,Borrowers(in thousands)": "74.1",
        "25 to 34,Dollars Outstanding (in billions)": "$3.89 ",
        "25 to 34,Borrowers (in thousands)": "130",
        "35 to 49,Dollars Outstanding(in billions)": "$4.90 ",
        "35 to 49,Borrowers (in thousands)": "114.6",
        "50 to 61,Dollars Outstanding (in billions)": "$2.14 ",
        "50 to 61,Borrowers (in thousands)": "50.1",
        "62 and Older,Dollars Outstanding (in billions)": "$0.65 ",
        "62 and Older,Borrowers (in thousands)": "15.7"
    },
    {
        "Location": "Kentucky",
        "24 or Younger,Dollars Outstanding(in billions)": "$1.45 ",
        "24 or Younger,Borrowers(in thousands)": "102",
        "25 to 34,Dollars Outstanding (in billions)": "$6.66 ",
        "25 to 34,Borrowers (in thousands)": "208.8",
        "35 to 49,Dollars Outstanding(in billions)": "$7.96 ",
        "35 to 49,Borrowers (in thousands)": "193.3",
        "50 to 61,Dollars Outstanding (in billions)": "$2.95 ",
        "50 to 61,Borrowers (in thousands)": "75.8",
        "62 and Older,Dollars Outstanding (in billions)": "$0.70 ",
        "62 and Older,Borrowers (in thousands)": "19.6"
    },
    {
        "Location": "Louisiana",
        "24 or Younger,Dollars Outstanding(in billions)": "$1.78 ",
        "24 or Younger,Borrowers(in thousands)": "128.9",
        "25 to 34,Dollars Outstanding (in billions)": "$7.22 ",
        "25 to 34,Borrowers (in thousands)": "217.1",
        "35 to 49,Dollars Outstanding(in billions)": "$9.03 ",
        "35 to 49,Borrowers (in thousands)": "194.1",
        "50 to 61,Dollars Outstanding (in billions)": "$3.39 ",
        "50 to 61,Borrowers (in thousands)": "80.8",
        "62 and Older,Dollars Outstanding (in billions)": "$1.06 ",
        "62 and Older,Borrowers (in thousands)": "28.7"
    },
    {
        "Location": "Maine",
        "24 or Younger,Dollars Outstanding(in billions)": "$0.56 ",
        "24 or Younger,Borrowers(in thousands)": "37.5",
        "25 to 34,Dollars Outstanding (in billions)": "$2.13 ",
        "25 to 34,Borrowers (in thousands)": "67",
        "35 to 49,Dollars Outstanding(in billions)": "$2.18 ",
        "35 to 49,Borrowers (in thousands)": "51.2",
        "50 to 61,Dollars Outstanding (in billions)": "$0.99 ",
        "50 to 61,Borrowers (in thousands)": "23.2",
        "62 and Older,Dollars Outstanding (in billions)": "$0.36 ",
        "62 and Older,Borrowers (in thousands)": "7.6"
    },
    {
        "Location": "Maryland",
        "24 or Younger,Dollars Outstanding(in billions)": "$2.26 ",
        "24 or Younger,Borrowers(in thousands)": "144.4",
        "25 to 34,Dollars Outstanding (in billions)": "$10.90 ",
        "25 to 34,Borrowers (in thousands)": "280.7",
        "35 to 49,Dollars Outstanding(in billions)": "$13.41 ",
        "35 to 49,Borrowers (in thousands)": "241.8",
        "50 to 61,Dollars Outstanding (in billions)": "$7.03 ",
        "50 to 61,Borrowers (in thousands)": "124.8",
        "62 and Older,Dollars Outstanding (in billions)": "$2.33 ",
        "62 and Older,Borrowers (in thousands)": "43.2"
    },
    {
        "Location": "Massachusetts",
        "24 or Younger,Dollars Outstanding(in billions)": "$3.60 ",
        "24 or Younger,Borrowers(in thousands)": "223.9",
        "25 to 34,Dollars Outstanding (in billions)": "$12.06 ",
        "25 to 34,Borrowers (in thousands)": "342.6",
        "35 to 49,Dollars Outstanding(in billions)": "$8.86 ",
        "35 to 49,Borrowers (in thousands)": "197.8",
        "50 to 61,Dollars Outstanding (in billions)": "$4.51 ",
        "50 to 61,Borrowers (in thousands)": "95.3",
        "62 and Older,Dollars Outstanding (in billions)": "$1.77 ",
        "62 and Older,Borrowers (in thousands)": "35.3"
    },
    {
        "Location": "Michigan",
        "24 or Younger,Dollars Outstanding(in billions)": "$3.83 ",
        "24 or Younger,Borrowers(in thousands)": "247.1",
        "25 to 34,Dollars Outstanding (in billions)": "$17.31 ",
        "25 to 34,Borrowers (in thousands)": "492.1",
        "35 to 49,Dollars Outstanding(in billions)": "$18.80 ",
        "35 to 49,Borrowers (in thousands)": "412.1",
        "50 to 61,Dollars Outstanding (in billions)": "$8.64 ",
        "50 to 61,Borrowers (in thousands)": "196.8",
        "62 and Older,Dollars Outstanding (in billions)": "$2.56 ",
        "62 and Older,Borrowers (in thousands)": "63.6"
    },
    {
        "Location": "Minnesota",
        "24 or Younger,Dollars Outstanding(in billions)": "$2.41 ",
        "24 or Younger,Borrowers(in thousands)": "167.5",
        "25 to 34,Dollars Outstanding (in billions)": "$9.41 ",
        "25 to 34,Borrowers (in thousands)": "293.6",
        "35 to 49,Dollars Outstanding(in billions)": "$9.96 ",
        "35 to 49,Borrowers (in thousands)": "219.8",
        "50 to 61,Dollars Outstanding (in billions)": "$3.73 ",
        "50 to 61,Borrowers (in thousands)": "84.1",
        "62 and Older,Dollars Outstanding (in billions)": "$1.09 ",
        "62 and Older,Borrowers (in thousands)": "25.6"
    },
    {
        "Location": "Mississippi",
        "24 or Younger,Dollars Outstanding(in billions)": "$0.98 ",
        "24 or Younger,Borrowers(in thousands)": "73.2",
        "25 to 34,Dollars Outstanding (in billions)": "$4.64 ",
        "25 to 34,Borrowers (in thousands)": "142.9",
        "35 to 49,Dollars Outstanding(in billions)": "$7.05 ",
        "35 to 49,Borrowers (in thousands)": "141",
        "50 to 61,Dollars Outstanding (in billions)": "$2.74 ",
        "50 to 61,Borrowers (in thousands)": "60.6",
        "62 and Older,Dollars Outstanding (in billions)": "$0.80 ",
        "62 and Older,Borrowers (in thousands)": "19.9"
    },
    {
        "Location": "Missouri",
        "24 or Younger,Dollars Outstanding(in billions)": "$2.03 ",
        "24 or Younger,Borrowers(in thousands)": "139.1",
        "25 to 34,Dollars Outstanding (in billions)": "$9.31 ",
        "25 to 34,Borrowers (in thousands)": "284.4",
        "35 to 49,Dollars Outstanding(in billions)": "$11.63 ",
        "35 to 49,Borrowers (in thousands)": "257.1",
        "50 to 61,Dollars Outstanding (in billions)": "$5.08 ",
        "50 to 61,Borrowers (in thousands)": "115.3",
        "62 and Older,Dollars Outstanding (in billions)": "$1.55 ",
        "62 and Older,Borrowers (in thousands)": "37.7"
    },
    {
        "Location": "Montana",
        "24 or Younger,Dollars Outstanding(in billions)": "$0.26 ",
        "24 or Younger,Borrowers(in thousands)": "21.1",
        "25 to 34,Dollars Outstanding (in billions)": "$1.29 ",
        "25 to 34,Borrowers (in thousands)": "43.7",
        "35 to 49,Dollars Outstanding(in billions)": "$1.75 ",
        "35 to 49,Borrowers (in thousands)": "39.3",
        "50 to 61,Dollars Outstanding (in billions)": "$0.70 ",
        "50 to 61,Borrowers (in thousands)": "16.7",
        "62 and Older,Dollars Outstanding (in billions)": "$0.24 ",
        "62 and Older,Borrowers (in thousands)": "5.7"
    },
    {
        "Location": "Nebraska",
        "24 or Younger,Dollars Outstanding(in billions)": "$0.74 ",
        "24 or Younger,Borrowers(in thousands)": "53.8",
        "25 to 34,Dollars Outstanding (in billions)": "$2.76 ",
        "25 to 34,Borrowers (in thousands)": "87.6",
        "35 to 49,Dollars Outstanding(in billions)": "$2.88 ",
        "35 to 49,Borrowers (in thousands)": "67.8",
        "50 to 61,Dollars Outstanding (in billions)": "$1.24 ",
        "50 to 61,Borrowers (in thousands)": "30.1",
        "62 and Older,Dollars Outstanding (in billions)": "$0.35 ",
        "62 and Older,Borrowers (in thousands)": "8.8"
    },
    {
        "Location": "Nevada",
        "24 or Younger,Dollars Outstanding(in billions)": "$0.55 ",
        "24 or Younger,Borrowers(in thousands)": "46.5",
        "25 to 34,Dollars Outstanding (in billions)": "$3.55 ",
        "25 to 34,Borrowers (in thousands)": "119.7",
        "35 to 49,Dollars Outstanding(in billions)": "$4.80 ",
        "35 to 49,Borrowers (in thousands)": "112.3",
        "50 to 61,Dollars Outstanding (in billions)": "$2.10 ",
        "50 to 61,Borrowers (in thousands)": "50.1",
        "62 and Older,Dollars Outstanding (in billions)": "$0.75 ",
        "62 and Older,Borrowers (in thousands)": "18.9"
    },
    {
        "Location": "New Hampshire",
        "24 or Younger,Dollars Outstanding(in billions)": "$0.67 ",
        "24 or Younger,Borrowers(in thousands)": "43.5",
        "25 to 34,Dollars Outstanding (in billions)": "$2.20 ",
        "25 to 34,Borrowers (in thousands)": "69.9",
        "35 to 49,Dollars Outstanding(in billions)": "$2.02 ",
        "35 to 49,Borrowers (in thousands)": "45.4",
        "50 to 61,Dollars Outstanding (in billions)": "$1.20 ",
        "50 to 61,Borrowers (in thousands)": "24",
        "62 and Older,Dollars Outstanding (in billions)": "$0.38 ",
        "62 and Older,Borrowers (in thousands)": "7.3"
    },
    {
        "Location": "New Jersey",
        "24 or Younger,Dollars Outstanding(in billions)": "$4.50 ",
        "24 or Younger,Borrowers(in thousands)": "281.6",
        "25 to 34,Dollars Outstanding (in billions)": "$15.16 ",
        "25 to 34,Borrowers (in thousands)": "430.8",
        "35 to 49,Dollars Outstanding(in billions)": "$12.31 ",
        "35 to 49,Borrowers (in thousands)": "272.2",
        "50 to 61,Dollars Outstanding (in billions)": "$7.70 ",
        "50 to 61,Borrowers (in thousands)": "150.9",
        "62 and Older,Dollars Outstanding (in billions)": "$2.78 ",
        "62 and Older,Borrowers (in thousands)": "54.7"
    },
    {
        "Location": "New Mexico",
        "24 or Younger,Dollars Outstanding(in billions)": "$0.31 ",
        "24 or Younger,Borrowers(in thousands)": "27.3",
        "25 to 34,Dollars Outstanding (in billions)": "$2.08 ",
        "25 to 34,Borrowers (in thousands)": "74.7",
        "35 to 49,Dollars Outstanding(in billions)": "$3.41 ",
        "35 to 49,Borrowers (in thousands)": "80.2",
        "50 to 61,Dollars Outstanding (in billions)": "$1.41 ",
        "50 to 61,Borrowers (in thousands)": "33.1",
        "62 and Older,Dollars Outstanding (in billions)": "$0.55 ",
        "62 and Older,Borrowers (in thousands)": "12.4"
    },
    {
        "Location": "New York",
        "24 or Younger,Dollars Outstanding(in billions)": "$8.05 ",
        "24 or Younger,Borrowers(in thousands)": "502.1",
        "25 to 34,Dollars Outstanding (in billions)": "$33.80 ",
        "25 to 34,Borrowers (in thousands)": "886.7",
        "35 to 49,Dollars Outstanding(in billions)": "$29.77 ",
        "35 to 49,Borrowers (in thousands)": "609",
        "50 to 61,Dollars Outstanding (in billions)": "$15.53 ",
        "50 to 61,Borrowers (in thousands)": "322.7",
        "62 and Older,Dollars Outstanding (in billions)": "$5.79 ",
        "62 and Older,Borrowers (in thousands)": "127.9"
    },
    {
        "Location": "North Carolina",
        "24 or Younger,Dollars Outstanding(in billions)": "$3.70 ",
        "24 or Younger,Borrowers(in thousands)": "242.2",
        "25 to 34,Dollars Outstanding (in billions)": "$15.87 ",
        "25 to 34,Borrowers (in thousands)": "444.5",
        "35 to 49,Dollars Outstanding(in billions)": "$18.80 ",
        "35 to 49,Borrowers (in thousands)": "383.5",
        "50 to 61,Dollars Outstanding (in billions)": "$8.39 ",
        "50 to 61,Borrowers (in thousands)": "179.1",
        "62 and Older,Dollars Outstanding (in billions)": "$2.30 ",
        "62 and Older,Borrowers (in thousands)": "51.6"
    },
    {
        "Location": "North Dakota",
        "24 or Younger,Dollars Outstanding(in billions)": "$0.29 ",
        "24 or Younger,Borrowers(in thousands)": "21.3",
        "25 to 34,Dollars Outstanding (in billions)": "$0.91 ",
        "25 to 34,Borrowers (in thousands)": "33.2",
        "35 to 49,Dollars Outstanding(in billions)": "$0.96 ",
        "35 to 49,Borrowers (in thousands)": "23.2",
        "50 to 61,Dollars Outstanding (in billions)": "$0.30 ",
        "50 to 61,Borrowers (in thousands)": "7.5",
        "62 and Older,Dollars Outstanding (in billions)": "$0.09 ",
        "62 and Older,Borrowers (in thousands)": "2.2"
    },
    {
        "Location": "Ohio",
        "24 or Younger,Dollars Outstanding(in billions)": "$4.74 ",
        "24 or Younger,Borrowers(in thousands)": "320.9",
        "25 to 34,Dollars Outstanding (in billions)": "$20.00 ",
        "25 to 34,Borrowers (in thousands)": "607.9",
        "35 to 49,Dollars Outstanding(in billions)": "$23.56 ",
        "35 to 49,Borrowers (in thousands)": "541",
        "50 to 61,Dollars Outstanding (in billions)": "$10.84 ",
        "50 to 61,Borrowers (in thousands)": "245.7",
        "62 and Older,Dollars Outstanding (in billions)": "$3.36 ",
        "62 and Older,Borrowers (in thousands)": "81.5"
    },
    {
        "Location": "Oklahoma",
        "24 or Younger,Dollars Outstanding(in billions)": "$0.95 ",
        "24 or Younger,Borrowers(in thousands)": "74.7",
        "25 to 34,Dollars Outstanding (in billions)": "$4.40 ",
        "25 to 34,Borrowers (in thousands)": "157.3",
        "35 to 49,Dollars Outstanding(in billions)": "$6.46 ",
        "35 to 49,Borrowers (in thousands)": "162.5",
        "50 to 61,Dollars Outstanding (in billions)": "$2.71 ",
        "50 to 61,Borrowers (in thousands)": "68.2",
        "62 and Older,Dollars Outstanding (in billions)": "$0.89 ",
        "62 and Older,Borrowers (in thousands)": "23.6"
    },
    {
        "Location": "Oregon",
        "24 or Younger,Dollars Outstanding(in billions)": "$0.92 ",
        "24 or Younger,Borrowers(in thousands)": "69.3",
        "25 to 34,Dollars Outstanding (in billions)": "$6.13 ",
        "25 to 34,Borrowers (in thousands)": "186.6",
        "35 to 49,Dollars Outstanding(in billions)": "$8.83 ",
        "35 to 49,Borrowers (in thousands)": "187",
        "50 to 61,Dollars Outstanding (in billions)": "$3.16 ",
        "50 to 61,Borrowers (in thousands)": "71.6",
        "62 and Older,Dollars Outstanding (in billions)": "$1.15 ",
        "62 and Older,Borrowers (in thousands)": "26.5"
    },
    {
        "Location": "Pennsylvania",
        "24 or Younger,Dollars Outstanding(in billions)": "$6.48 ",
        "24 or Younger,Borrowers(in thousands)": "405.1",
        "25 to 34,Dollars Outstanding (in billions)": "$23.17 ",
        "25 to 34,Borrowers (in thousands)": "661",
        "35 to 49,Dollars Outstanding(in billions)": "$20.74 ",
        "35 to 49,Borrowers (in thousands)": "447.2",
        "50 to 61,Dollars Outstanding (in billions)": "$10.84 ",
        "50 to 61,Borrowers (in thousands)": "231",
        "62 and Older,Dollars Outstanding (in billions)": "$3.42 ",
        "62 and Older,Borrowers (in thousands)": "75.1"
    },
    {
        "Location": "Puerto Rico",
        "24 or Younger,Dollars Outstanding(in billions)": "$0.52 ",
        "24 or Younger,Borrowers(in thousands)": "49.5",
        "25 to 34,Dollars Outstanding (in billions)": "$3.51 ",
        "25 to 34,Borrowers (in thousands)": "122.2",
        "35 to 49,Dollars Outstanding(in billions)": "$3.76 ",
        "35 to 49,Borrowers (in thousands)": "105.9",
        "50 to 61,Dollars Outstanding (in billions)": "$1.13 ",
        "50 to 61,Borrowers (in thousands)": "36.9",
        "62 and Older,Dollars Outstanding (in billions)": "$0.32 ",
        "62 and Older,Borrowers (in thousands)": "11.8"
    },
    {
        "Location": "Rhode Island",
        "24 or Younger,Dollars Outstanding(in billions)": "$0.47 ",
        "24 or Younger,Borrowers(in thousands)": "30.7",
        "25 to 34,Dollars Outstanding (in billions)": "$1.74 ",
        "25 to 34,Borrowers (in thousands)": "54",
        "35 to 49,Dollars Outstanding(in billions)": "$1.38 ",
        "35 to 49,Borrowers (in thousands)": "34.1",
        "50 to 61,Dollars Outstanding (in billions)": "$0.73 ",
        "50 to 61,Borrowers (in thousands)": "17",
        "62 and Older,Dollars Outstanding (in billions)": "$0.28 ",
        "62 and Older,Borrowers (in thousands)": "5.9"
    },
    {
        "Location": "South Carolina",
        "24 or Younger,Dollars Outstanding(in billions)": "$2.05 ",
        "24 or Younger,Borrowers(in thousands)": "134.3",
        "25 to 34,Dollars Outstanding (in billions)": "$9.00 ",
        "25 to 34,Borrowers (in thousands)": "246.7",
        "35 to 49,Dollars Outstanding(in billions)": "$10.91 ",
        "35 to 49,Borrowers (in thousands)": "217.2",
        "50 to 61,Dollars Outstanding (in billions)": "$4.74 ",
        "50 to 61,Borrowers (in thousands)": "99.5",
        "62 and Older,Dollars Outstanding (in billions)": "$1.35 ",
        "62 and Older,Borrowers (in thousands)": "31"
    },
    {
        "Location": "South Dakota",
        "24 or Younger,Dollars Outstanding(in billions)": "$0.40 ",
        "24 or Younger,Borrowers(in thousands)": "28.1",
        "25 to 34,Dollars Outstanding (in billions)": "$1.26 ",
        "25 to 34,Borrowers (in thousands)": "41.6",
        "35 to 49,Dollars Outstanding(in billions)": "$1.33 ",
        "35 to 49,Borrowers (in thousands)": "30.4",
        "50 to 61,Dollars Outstanding (in billions)": "$0.50 ",
        "50 to 61,Borrowers (in thousands)": "12.5",
        "62 and Older,Dollars Outstanding (in billions)": "$0.16 ",
        "62 and Older,Borrowers (in thousands)": "3.9"
    },
    {
        "Location": "Tennessee",
        "24 or Younger,Dollars Outstanding(in billions)": "$2.04 ",
        "24 or Younger,Borrowers(in thousands)": "141.7",
        "25 to 34,Dollars Outstanding (in billions)": "$10.40 ",
        "25 to 34,Borrowers (in thousands)": "308.1",
        "35 to 49,Dollars Outstanding(in billions)": "$12.38 ",
        "35 to 49,Borrowers (in thousands)": "263.7",
        "50 to 61,Dollars Outstanding (in billions)": "$5.13 ",
        "50 to 61,Borrowers (in thousands)": "113.3",
        "62 and Older,Dollars Outstanding (in billions)": "$1.42 ",
        "62 and Older,Borrowers (in thousands)": "33"
    },
    {
        "Location": "Texas",
        "24 or Younger,Dollars Outstanding(in billions)": "$8.43 ",
        "24 or Younger,Borrowers(in thousands)": "642.5",
        "25 to 34,Dollars Outstanding (in billions)": "$37.77 ",
        "25 to 34,Borrowers (in thousands)": "1,268.00",
        "35 to 49,Dollars Outstanding(in billions)": "$47.84 ",
        "35 to 49,Borrowers (in thousands)": "1,110.20",
        "50 to 61,Dollars Outstanding (in billions)": "$19.84 ",
        "50 to 61,Borrowers (in thousands)": "459.8",
        "62 and Older,Dollars Outstanding (in billions)": "$5.79 ",
        "62 and Older,Borrowers (in thousands)": "144.4"
    },
    {
        "Location": "Utah",
        "24 or Younger,Dollars Outstanding(in billions)": "$0.55 ",
        "24 or Younger,Borrowers(in thousands)": "51.7",
        "25 to 34,Dollars Outstanding (in billions)": "$3.44 ",
        "25 to 34,Borrowers (in thousands)": "120.7",
        "35 to 49,Dollars Outstanding(in billions)": "$4.57 ",
        "35 to 49,Borrowers (in thousands)": "100.7",
        "50 to 61,Dollars Outstanding (in billions)": "$1.17 ",
        "50 to 61,Borrowers (in thousands)": "27",
        "62 and Older,Dollars Outstanding (in billions)": "$0.34 ",
        "62 and Older,Borrowers (in thousands)": "7.6"
    },
    {
        "Location": "Vermont",
        "24 or Younger,Dollars Outstanding(in billions)": "$0.26 ",
        "24 or Younger,Borrowers(in thousands)": "17.1",
        "25 to 34,Dollars Outstanding (in billions)": "$0.92 ",
        "25 to 34,Borrowers (in thousands)": "27.4",
        "35 to 49,Dollars Outstanding(in billions)": "$0.99 ",
        "35 to 49,Borrowers (in thousands)": "19.3",
        "50 to 61,Dollars Outstanding (in billions)": "$0.51 ",
        "50 to 61,Borrowers (in thousands)": "9.7",
        "62 and Older,Dollars Outstanding (in billions)": "$0.22 ",
        "62 and Older,Borrowers (in thousands)": "3.8"
    },
    {
        "Location": "Virginia",
        "24 or Younger,Dollars Outstanding(in billions)": "$3.18 ",
        "24 or Younger,Borrowers(in thousands)": "205.6",
        "25 to 34,Dollars Outstanding (in billions)": "$13.99 ",
        "25 to 34,Borrowers (in thousands)": "376.7",
        "35 to 49,Dollars Outstanding(in billions)": "$15.88 ",
        "35 to 49,Borrowers (in thousands)": "312",
        "50 to 61,Dollars Outstanding (in billions)": "$7.28 ",
        "50 to 61,Borrowers (in thousands)": "142.2",
        "62 and Older,Dollars Outstanding (in billions)": "$2.16 ",
        "62 and Older,Borrowers (in thousands)": "44.4"
    },
    {
        "Location": "Washington",
        "24 or Younger,Dollars Outstanding(in billions)": "$1.50 ",
        "24 or Younger,Borrowers(in thousands)": "113.1",
        "25 to 34,Dollars Outstanding (in billions)": "$8.82 ",
        "25 to 34,Borrowers (in thousands)": "275.7",
        "35 to 49,Dollars Outstanding(in billions)": "$11.39 ",
        "35 to 49,Borrowers (in thousands)": "253.4",
        "50 to 61,Dollars Outstanding (in billions)": "$4.71 ",
        "50 to 61,Borrowers (in thousands)": "106.3",
        "62 and Older,Dollars Outstanding (in billions)": "$1.60 ",
        "62 and Older,Borrowers (in thousands)": "36.3"
    },
    {
        "Location": "West Virginia",
        "24 or Younger,Dollars Outstanding(in billions)": "$0.57 ",
        "24 or Younger,Borrowers(in thousands)": "40.8",
        "25 to 34,Dollars Outstanding (in billions)": "$2.34 ",
        "25 to 34,Borrowers (in thousands)": "74.7",
        "35 to 49,Dollars Outstanding(in billions)": "$2.94 ",
        "35 to 49,Borrowers (in thousands)": "73.9",
        "50 to 61,Dollars Outstanding (in billions)": "$1.10 ",
        "50 to 61,Borrowers (in thousands)": "29.3",
        "62 and Older,Dollars Outstanding (in billions)": "$0.30 ",
        "62 and Older,Borrowers (in thousands)": "8.6"
    },
    {
        "Location": "Wisconsin",
        "24 or Younger,Dollars Outstanding(in billions)": "$2.23 ",
        "24 or Younger,Borrowers(in thousands)": "154.5",
        "25 to 34,Dollars Outstanding (in billions)": "$8.35 ",
        "25 to 34,Borrowers (in thousands)": "268.7",
        "35 to 49,Dollars Outstanding(in billions)": "$8.46 ",
        "35 to 49,Borrowers (in thousands)": "202.1",
        "50 to 61,Dollars Outstanding (in billions)": "$3.35 ",
        "50 to 61,Borrowers (in thousands)": "79.4",
        "62 and Older,Dollars Outstanding (in billions)": "$0.95 ",
        "62 and Older,Borrowers (in thousands)": "23"
    },
    {
        "Location": "Wyoming",
        "24 or Younger,Dollars Outstanding(in billions)": "$0.09 ",
        "24 or Younger,Borrowers(in thousands)": "8.5",
        "25 to 34,Dollars Outstanding (in billions)": "$0.47 ",
        "25 to 34,Borrowers (in thousands)": "17.9",
        "35 to 49,Dollars Outstanding(in billions)": "$0.74 ",
        "35 to 49,Borrowers (in thousands)": "18.5",
        "50 to 61,Dollars Outstanding (in billions)": "$0.28 ",
        "50 to 61,Borrowers (in thousands)": "7",
        "62 and Older,Dollars Outstanding (in billions)": "$0.09 ",
        "62 and Older,Borrowers (in thousands)": "2.2"
    },
    {
        "Location": "Other",
        "24 or Younger,Dollars Outstanding(in billions)": "$0.17 ",
        "24 or Younger,Borrowers(in thousands)": "13.5",
        "25 to 34,Dollars Outstanding (in billions)": "$1.33 ",
        "25 to 34,Borrowers (in thousands)": "35",
        "35 to 49,Dollars Outstanding(in billions)": "$1.88 ",
        "35 to 49,Borrowers (in thousands)": "29.8",
        "50 to 61,Dollars Outstanding (in billions)": "$0.66 ",
        "50 to 61,Borrowers (in thousands)": "11.3",
        "62 and Older,Dollars Outstanding (in billions)": "$0.24 ",
        "62 and Older,Borrowers (in thousands)": "4.3"
    },
    {
        "Location": "Not Reported",
        "24 or Younger,Dollars Outstanding(in billions)": "$0.02 ",
        "24 or Younger,Borrowers(in thousands)": "5.1",
        "25 to 34,Dollars Outstanding (in billions)": "$1.23 ",
        "25 to 34,Borrowers (in thousands)": "171.7",
        "35 to 49,Dollars Outstanding(in billions)": "$52.63 ",
        "35 to 49,Borrowers (in thousands)": "2,186.80",
        "50 to 61,Dollars Outstanding (in billions)": "$27.92 ",
        "50 to 61,Borrowers (in thousands)": "875.3",
        "62 and Older,Dollars Outstanding (in billions)": "$16.07 ",
        "62 and Older,Borrowers (in thousands)": "579.8"
    }
]